{
  "date": "24.08.2025",
  "time": "15:00",
  "place": "Кофейня \"Том Сойер\", ул. Шмидта, 12",
  "film": "Сердце мира",
  "director": "Наталия Мещанинова",
  "genre": "Драма",
  "country": "Россия, Литва",
  "year": "2018",
  "poster": "https://sun9-86.vkuserphoto.ru/s/v1/ig2/LQjVl4gphJQmG3qGa7R6Y2tCzDXCjfqBbbA9lWLxsoLSsyVi70AOooWkQ3Z5HW5gRFIwdQb2hyk56sRxRl1ErvdN.jpg?quality=95&as=32x46,48x69,72x103,108x154,160x229,240x343,360x514,480x686,540x771,640x914,720x1029,1080x1543,1260x1800&from=bu&cs=1260x0",
  "discussionNumber": "254",
  "description": "",
  "requirements": "Рекомендуем посмотреть фильм заранее"
}